commonitor/__init__.py
commonitor/commonitor.py
commonitor/icons/icons8-usb-connected-96.png
commonitor/icons/icons8-usb-disconnected-96.png
commonitor/icons/system-monitor.png
com_monitor-0.1.1.post1.dist-info/entry_points.txt
com_monitor-0.1.1.post1.dist-info/LICENSE
com_monitor-0.1.1.post1.dist-info/WHEEL
com_monitor-0.1.1.post1.dist-info/METADATA
com_monitor-0.1.1.post1.dist-info/RECORD
