Metadata-Version: 2.1
Name: com-monitor
Version: 0.1.1.post1
Summary: ComMonitor: A small system tray utility that provides system notifications when COM port devices are added to or removed from the system.
Author-email: Josh Burnett <josh@burnettsonline.org>
Requires-Python: >=3.8
Classifier: License :: OSI Approved :: MIT License
Requires-Dist: windows_toasts
Requires-Dist: pyserial
Requires-Dist: PySide6
Project-URL: Home, https://github.com/joshburnett/COM-Port-Monitor
